dtfpy/__init__.py
dtfpy/applications/__init__.py
dtfpy/applications/main.py
dtfpy/applications/sub.py
dtfpy/controllers/__init__.py
dtfpy/controllers/monitoring.py
dtfpy/databases/__init__.py
dtfpy/databases/database.py
dtfpy/databases/redis.py
dtfpy/middlewares/__init__.py
dtfpy/middlewares/authentication.py
dtfpy/middlewares/http_exception.py
dtfpy/middlewares/runtime.py
dtfpy/middlewares/validation_exception.py
dtfpy/routes/__init__.py
dtfpy/routes/response.py
dtfpy/routes/route.py
dtfpy/routes/router.py
dtfpy/schemas/__init__.py
dtfpy/schemas/helpers.py
dtfpy/schemas/search.py
dtfpy/storages/__init__.py
dtfpy/storages/bucket.py
dtfpy/storages/file_folder.py
dtfpy/storages/ftp.py
dtfpy/utilities/__init__.py
dtfpy/utilities/constants.py
dtfpy/utilities/exception.py
dtfpy/utilities/helpers.py
dtfpy/utilities/jwt_encryption.py
dtfpy/utilities/logging.py
dtfpy/utilities/model.py
dtfpy/utilities/search.py
dtfpy/utilities/settings.py
dtfpy/workers/__init__.py
dtfpy/workers/main.py
dtfpy/wrappers/__init__.py
dtfpy/wrappers/rate_limiter.py
dtfpy/wrappers/retry.py
dtfpy-1.0.8.dist-info/METADATA
dtfpy-1.0.8.dist-info/WHEEL
dtfpy-1.0.8.dist-info/RECORD
